<odoo>
    <data>
        <!-- Severity Master data files -->
        <record id="kw_guest_house_data1" model="kw_facilities_master">
            <field name="facility_name">Meeting Room with Monitor</field>
            <field name="code">MRM</field>
            <field name="active">True</field>
        </record>
        <record id="kw_guest_house_data2" model="kw_facilities_master">
            <field name="facility_name">Vehicle</field>
            <field name="code">VH</field>
            <field name="active">True</field>
        </record>
        <record id="kw_guest_house_data3" model="kw_facilities_master">
            <field name="facility_name">Washing Machine</field>
            <field name="code">WM</field>
            <field name="active">True</field>

        </record>
        <record id="kw_guest_house_data4" model="kw_facilities_master">
            <field name="facility_name">Cooking Gas, Stove</field>
            <field name="code">CGS</field>
            <field name="active">True</field>

        </record>
        <record id="kw_guest_house_data5" model="kw_facilities_master">
            <field name="facility_name">Utensils</field>
            <field name="code">UTNSL</field>
            <field name="active">True</field>

        </record>
        <record id="kw_guest_house_data6" model="kw_facilities_master">
            <field name="facility_name">Electric Iron</field>
            <field name="code">EI</field>
            <field name="active">True</field>

        </record>
        <record id="kw_guest_house_data7" model="kw_facilities_master">
            <field name="facility_name">Geyser</field>
            <field name="code">GSR</field>
            <field name="active">True</field>

        </record>
        <record id="kw_guest_house_data8" model="kw_facilities_master">
            <field name="facility_name">Refrigerator</field>
            <field name="code">FRIJ</field>
            <field name="active">True</field>

        </record>
        <record id="kw_guest_house_data9" model="kw_facilities_master">
            <field name="facility_name">Maid</field>
            <field name="code">MD</field>
            <field name="active">True</field>

        </record>
        <record id="kw_guest_house_data10" model="kw_facilities_master">
            <field name="facility_name">Lift</field>
            <field name="code">LFT</field>
            <field name="active">True</field>

        </record>
    </data>
</odoo>
