<?xml version="1.0" encoding="utf-8"?>
<odoo>
    <data>
        <record id="hr_religion_view_tree" model="ir.ui.view">
            <field name="name">employee.religion.tree</field>
            <field name="model">employee.religion</field>
            <field name="arch" type="xml">
                <tree string="Religion" editable="bottom">
                    <field name="name" string="Religion / धर्म" required="1"/>
                </tree>
            </field>
        </record>

        <record id="hr_religion_action" model="ir.actions.act_window">
            <field name="name">Religion / धर्म</field>
            <field name="res_model">employee.religion</field>
            <field name="view_mode">tree</field>
        </record>

        <menuitem
            id="hr_religion_sub_menu"
            name="Religion / धर्म"
            action="hr_religion_action"
            parent="hr.menu_human_resources_configuration"
            sequence="92"
            />
    </data>
</odoo>