<?xml version="1.0" encoding="utf-8"?>
<odoo>
    <record id="canteen_res_config_settings_view_form" model="ir.ui.view">
        <field name="name">res.config.settings.view.form.inherit.tds</field>
        <field name="model">res.config.settings</field>
        <field name="priority" eval="70"/>
        <field name="inherit_id" ref="base.res_config_settings_view_form"/>
        <field name="arch" type="xml">
            <xpath expr="//div[hasclass('settings')]" position="inside">
                <div class="app_settings_block" data-string="Canteen" string="Canteen" data-key="kw_canteen">
                    <h2>Canteen</h2>

                    <div class="row mt16 o_settings_container">
                        <div class="col-12 col-lg-12 o_setting_box" title="Date" id="date">
                            <div class="o_setting_right_pane">
                                <span class="o_form_label"></span>
                                <div class="text-muted"></div>
                                <div class="content-group">
                                    <div class="mt16 row">
                                        <label for="head_cook_ids" string="Head Cook" class="col-3 col-lg-3 o_light_label"/>
                                        <field name="head_cook_ids" widget="many2many_tags" options="{'no_open': True,'no_create':True,'no_edit':True}"/>
                                    </div>
                                    <div class="mt16 row">
                                        <label for="notify_cook_ids" string="Notify Cook" class="col-3 col-lg-3 o_light_label"/>
                                        <field name="notify_cook_ids" widget="many2many_tags" options="{'no_open': True,'no_create':True,'no_edit':True}"/>
                                    </div>
                                </div>
                            </div>
                        </div>
                    </div>
                </div>
            </xpath>
        </field>
    </record>

    <record id="canteen_config_settings_action" model="ir.actions.act_window">
        <field name="name">Settings</field>
        <field name="type">ir.actions.act_window</field>
        <field name="res_model">res.config.settings</field>
        <field name="view_mode">form</field>
        <field name="target">inline</field>
        <field name="context">{'module' : 'tds'}</field>
    </record>
</odoo>
